{
  "required": true,
  "package": "tech.lemonlime.configured.mixin",
  "compatibilityLevel": "JAVA_17",
  "mixins": [
    "feature.disableEnd.EndPortalBlockMixin",
    "feature.disableEndGateways.EndGatewayBlockEntityMixin",
    "feature.disableEndPortalFrameFilling.EnderEyeItemMixin",
    "feature.disableEyeOfEnderCasting.EnderEyeItemMixin",
    "feature.disableNether.NetherPortalBlockMixin",
    "feature.disablePlayerConnections.PlayerManagerMixin",
    "feature.disablePVP.MinecraftServerMixin",
    "feature.fakeHardcore.PlayerManagerMixin",
    "feature.motd.ServerMetadataMixin",
    "fix.stringDupeFix.TripwireBlockMixin"
  ],
  "injectors": {
    "defaultRequire": 0
	}
}